viz3dvideo/__init__.py
viz3dvideo/about.py
viz3dvideo/program.py
viz3dvideo/audio/__init__.py
viz3dvideo/audio/add.py
viz3dvideo/icons/logo.png
viz3dvideo/overlay/__init__.py
viz3dvideo/overlay/image.py
viz3dvideo/scatter/__init__.py
viz3dvideo/scatter/path.py
viz3dvideo/scatter/rotate.py
viz3dvideo/surf/__init__.py
viz3dvideo/surf/path.py
viz3dvideo/surf/rotate.py
viz3dvideo-0.1.1.dist-info/licenses/LICENSE
viz3dvideo-0.1.1.dist-info/METADATA
viz3dvideo-0.1.1.dist-info/WHEEL
viz3dvideo-0.1.1.dist-info/entry_points.txt
viz3dvideo-0.1.1.dist-info/top_level.txt
viz3dvideo-0.1.1.dist-info/RECORD
