Metadata-Version: 2.4
Name: viz3dvideo
Version: 0.1.1
Summary: Visualize a video of 3D graphs in Matplotlib
Author-email: Fernando Pujaico Rivera <fernando.pujaico.rivera@gmail.com>
Maintainer-email: Fernando Pujaico Rivera <fernando.pujaico.rivera@gmail.com>
License-Expression: GPL-3.0-only WITH Classpath-exception-2.0 OR BSD-3-Clause
Project-URL: Bug Reports, https://github.com/trucomanx/Viz3DVideo/issues
Project-URL: Funding, https://trucomanx.github.io/en/funding.html
Project-URL: Documentation, https://github.com/trucomanx/Viz3DVideo/tree/main/doc
Project-URL: Source, https://github.com/trucomanx/Viz3DVideo
Keywords: writing,translate
Classifier: Programming Language :: Python :: 3
Classifier: Operating System :: OS Independent
Requires-Python: >=3.8
License-File: LICENSE
Requires-Dist: matplotlib
Requires-Dist: moviepy
Dynamic: license-file
